{
  "version": "0.4.35",
  "flags": {},
  "shapes": [
    {
      "label": "main",
      "text": "",
      "points": [
        [
          902.5,
          410.625
        ],
        [
          1527.5,
          396.875
        ],
        [
          1529.375,
          995.0
        ],
        [
          923.125,
          1011.25
        ]
      ],
      "group_id": null,
      "shape_type": "polygon",
      "flags": {}
    }
  ],
  "imagePath": "C1.jpg",
  "imageData": null,
  "imageHeight": 1440,
  "imageWidth": 2560
}