{
  "version": "0.4.35",
  "flags": {},
  "shapes": [
    {
      "label": "main",
      "text": "",
      "points": [
        [
          1817.0,
          407.0
        ],
        [
          1243.0,
          427.0
        ],
        [
          1187.0,
          433.0
        ],
        [
          1112.0,
          431.0
        ],
        [
          1083.0,
          437.0
        ],
        [
          1079.0,
          450.0
        ],
        [
          1083.0,
          514.0
        ],
        [
          1080.0,
          569.0
        ],
        [
          1089.0,
          619.0
        ],
        [
          1087.0,
          682.0
        ],
        [
          1093.0,
          714.0
        ],
        [
          1088.0,
          744.0
        ],
        [
          1090.0,
          823.0
        ],
        [
          1097.0,
          839.0
        ],
        [
          1097.0,
          852.0
        ],
        [
          1091.0,
          857.0
        ],
        [
          1094.0,
          1049.0
        ],
        [
          1103.0,
          1092.0
        ],
        [
          1103.0,
          1128.0
        ],
        [
          1125.0,
          1162.0
        ],
        [
          1238.0,
          1167.0
        ],
        [
          1300.0,
          1161.0
        ],
        [
          1363.0,
          1164.0
        ],
        [
          1656.0,
          1158.0
        ],
        [
          1704.0,
          1149.0
        ],
        [
          1722.0,
          1153.0
        ],
        [
          1776.0,
          1149.0
        ],
        [
          1829.0,
          1122.0
        ],
        [
          1835.0,
          1086.0
        ],
        [
          1829.0,
          1032.0
        ],
        [
          1833.0,
          997.0
        ],
        [
          1823.0,
          790.0
        ],
        [
          1828.0,
          737.0
        ],
        [
          1825.0,
          666.0
        ],
        [
          1834.0,
          598.0
        ],
        [
          1828.0,
          584.0
        ],
        [
          1825.0,
          537.0
        ],
        [
          1830.0,
          438.0
        ],
        [
          1823.0,
          413.0
        ]
      ],
      "group_id": null,
      "shape_type": "polygon",
      "flags": {}
    }
  ],
  "imagePath": "B3.jpg",
  "imageData": null,
  "imageHeight": 1440,
  "imageWidth": 2560
}