{
  "version": "0.4.35",
  "flags": {},
  "shapes": [
    {
      "label": "main",
      "text": "",
      "points": [
        [
          849.1525423728814,
          621.6949152542372
        ],
        [
          852.542372881356,
          1164.0677966101696
        ],
        [
          1370.3389830508474,
          1174.2372881355932
        ],
        [
          1377.1186440677966,
          634.4067796610169
        ]
      ],
      "group_id": null,
      "shape_type": "polygon",
      "flags": {}
    }
  ],
  "imagePath": "B3.jpg",
  "imageData": null,
  "imageHeight": 1440,
  "imageWidth": 2560
}