{
  "version": "0.4.35",
  "flags": {},
  "shapes": [
    {
      "label": "main",
      "text": "",
      "points": [
        [
          189.6296296296298,
          583.3333333333333
        ],
        [
          1656.296296296296,
          574.074074074074
        ],
        [
          1698.8888888888887,
          1925.9259259259259
        ],
        [
          195.18518518518533,
          1922.2222222222222
        ]
      ],
      "group_id": null,
      "shape_type": "polygon",
      "flags": {}
    }
  ],
  "imagePath": "A3.jpeg",
  "imageData": null,
  "imageHeight": 2560,
  "imageWidth": 1920
}